pg_connection_handler/__init__.py
pg_connection_handler/database.py
pg_connection_handler/exceptions.py
tests/__init__.py
tests/test_package.py
pgsql_connection_handler-1.0.0b0.dist-info/LICENSE
pgsql_connection_handler-1.0.0b0.dist-info/METADATA
pgsql_connection_handler-1.0.0b0.dist-info/WHEEL
pgsql_connection_handler-1.0.0b0.dist-info/top_level.txt
pgsql_connection_handler-1.0.0b0.dist-info/RECORD
