Metadata-Version: 2.1
Name: pgsql-connection-handler
Version: 1.0.0b0
Summary: A package that connects to one or more PostgreSQL databases and allows you to retrieve a database connection when required. Depends on psycopg2-binary.
Home-page: https://github.com/armandtvz/pgsql-connection-handler
Author: Armandt van Zyl
Author-email: armandtvz@gmail.com
License: GPL-3.0
Classifier: Development Status :: 4 - Beta
Classifier: Intended Audience :: Developers
Classifier: License :: OSI Approved :: GNU General Public License v3 (GPLv3)
Classifier: Operating System :: OS Independent
Classifier: Programming Language :: Python
Classifier: Programming Language :: Python :: 3
Classifier: Programming Language :: Python :: 3.8
Classifier: Programming Language :: Python :: 3 :: Only
Requires-Python: >=3.8, <4
License-File: LICENSE
Requires-Dist: psycopg2-binary
